{
  "name": "Jackal Protocol",
  "categories": ["Infrastructure"],
  "main_category": "Infrastructure",
  "is_live": true,
  "is_featured": false,
  "is_trending": false,
  "url": "https://www.jackalprotocol.com/",
  "email": "",
  "phone": "",
  "location": "",
  "summary": "A blockchain delivering actually decentralized storage to all blockchains",
  "logo": "jackal.png",
  "cover": "Jackal-cover.png",
  "github": "https://github.com/JackalLabs/canine-chain",
  "twitter": "https://twitter.com/Jackal_Protocol",
  "discord": "https://discord.com/invite/5GKym3p6rj",
  "telegram": "https://t.me/+rtuZnbTlHaIzNjVh"
}
